BingoResearch/__init__.py
BingoResearch/module.py
BingoResearch-0.1.dist-info/LICENSE
BingoResearch-0.1.dist-info/METADATA
BingoResearch-0.1.dist-info/WHEEL
BingoResearch-0.1.dist-info/top_level.txt
BingoResearch-0.1.dist-info/RECORD
