Metadata-Version: 2.1
Name: BingoResearch
Version: 0.1
Summary: A toolbox for research
Home-page: https://github.com/EndlessBingo/BingoResearch
Author: gaomany
Author-email: 18580766357@163.com
Classifier: Programming Language :: Python :: 3
Classifier: License :: OSI Approved :: MIT License
Classifier: Operating System :: OS Independent
License-File: LICENSE
Requires-Dist: numpy
